mal/__init__.py
mal/_anime.py
mal/_anime_search.py
mal/_base.py
mal/_mal.py
mal/_manga.py
mal/_manga_search.py
mal/_search.py
mal/config.py
mal_api-0.5.3.dist-info/LICENSE
mal_api-0.5.3.dist-info/METADATA
mal_api-0.5.3.dist-info/WHEEL
mal_api-0.5.3.dist-info/top_level.txt
mal_api-0.5.3.dist-info/RECORD
