Metadata-Version: 2.1
Name: mal-api
Version: 0.5.3
Summary: A local MyAnimeList API 
Home-page: https://github.com/darenliang/mal-api
Author: Daren Liang
Author-email: darenliang@outlook.com
License: MIT
Keywords: api,myanimelist
Classifier: Programming Language :: Python :: 3
Classifier: License :: OSI Approved :: MIT License
Classifier: Operating System :: OS Independent
Requires-Python: >=3.6
License-File: LICENSE
Requires-Dist: requests
Requires-Dist: beautifulsoup4
